well_schematics/__init__.py
well_schematics/schematics.py
well_schematics-0.2.0.dist-info/METADATA
well_schematics-0.2.0.dist-info/RECORD
well_schematics-0.2.0.dist-info/WHEEL
well_schematics-0.2.0.dist-info/top_level.txt
