Metadata-Version: 2.1
Name: well-schematics
Version: 0.2.0
Summary: matplotlib code for drawing borehole schematic diagrams
Home-page: https://github.com/kinverarity1/well-schematics
Author: Kent Inverarity
Author-email: kinverarity@hotmail.com
License: MIT
Keywords: groundwater data
Platform: UNKNOWN
Classifier: Programming Language :: Python :: 3.5
Classifier: Programming Language :: Python :: 3.6
Requires-Dist: matplotlib
